{
  "duration": 2684,
  "ftp": 235.0,
  "items": [
    {
      "start": 0,
      "end": 2099,
      "duration": 2099,
      "classification": "recovery",
      "average_power": 81.89375966993296,
      "peak_power": 301.0,
      "normalized_power": 95.35940262069576,
      "intensity_factor": 0.4057846920029607,
      "power_ratio": 0.3484840837018424,
      "time_above_95": 0.006704486848891181,
      "time_above_106": 0.0025786487880350697,
      "time_above_120": 0.0005157297576070139,
      "time_above_150": 0.0,
      "heart_rate_avg": 124.3233625580196,
      "heart_rate_max": 135,
      "heart_rate_slope": 0.0,
      "metadata": {
        "hr_percent_max": 0.6375557054257415
      }
    },
    {
      "start": 2099,
      "end": 2230,
      "duration": 131,
      "classification": "endurance",
      "average_power": 143.33587786259542,
      "peak_power": 224.0,
      "normalized_power": 141.75073416276516,
      "intensity_factor": 0.6031946134585752,
      "power_ratio": 0.6099399057982784,
      "time_above_95": 0.007633587786259542,
      "time_above_106": 0.0,
      "time_above_120": 0.0,
      "time_above_150": 0.0,
      "heart_rate_avg": 131.48091603053436,
      "heart_rate_max": 135,
      "heart_rate_slope": 0.10687022900763359,
      "metadata": {
        "hr_percent_max": 0.6742611078488941
      }
    },
    {
      "start": 2230,
      "end": 2685,
      "duration": 615,
      "classification": "recovery",
      "average_power": 56.81951219512195,
      "peak_power": 246.0,
      "normalized_power": 83.18222875118497,
      "intensity_factor": 0.35396693085610625,
      "power_ratio": 0.2417851582771147,
      "time_above_95": 0.011382113821138212,
      "time_above_106": 0.0,
      "time_above_120": 0.0,
      "time_above_150": 0.0,
      "heart_rate_avg": 118.4130081300813,
      "heart_rate_max": 136,
      "heart_rate_slope": -0.01951219512195122,
      "metadata": {
        "hr_percent_max": 0.6072461955388785
      }
    }
  ],
  "preview_image": "data/zone_previews/strava_15314397088_zones.png",
  "zone_segments": [
    {
      "metric": "power",
      "zone": "Z1",
      "label": "Active Recovery",
      "start_time": 0.0,
      "end_time": 34.02852614896989,
      "duration_seconds": 34.02852614896989,
      "height": 0.250705996131528,
      "intensity_ratio": 0.3594414893617021,
      "average_value": 84.46875
    },
    {
      "metric": "power",
      "zone": "Z1",
      "label": "Active Recovery",
      "start_time": 34.02852614896989,
      "end_time": 79.75435816164817,
      "duration_seconds": 41.47226624405705,
      "height": 0.2626771809750533,
      "intensity_ratio": 0.3923622476813966,
      "average_value": 92.2051282051282
    },
    {
      "metric": "power",
      "zone": "Z1",
      "label": "Active Recovery",
      "start_time": 79.75435816164817,
      "end_time": 87.19809825673534,
      "duration_seconds": 7.443740095087163,
      "height": 0.2544017684443216,
      "intensity_ratio": 0.3696048632218845,
      "average_value": 86.85714285714286
    },
    {
      "metric": "power",
      "zone": "Z2",
      "label": "Endurance",
      "start_time": 87.19809825673534,
      "end_time": 101.02218700475436,
      "duration_seconds": 13.824088748019017,
      "height": 0.32,
      "intensity_ratio": 0.5374795417348609,
      "average_value": 126.3076923076923
    },
    {
      "metric": "power",
      "zone": "Z1",
      "label": "Active Recovery",
      "start_time": 101.02218700475436,
      "end_time": 122.29001584786053,
      "duration_seconds": 21.26782884310618,
      "height": 0.3082398452611218,
      "intensity_ratio": 0.5176595744680851,
      "average_value": 121.65
    },
    {
      "metric": "power",
      "zone": "Z2",
      "label": "Endurance",
      "start_time": 122.29001584786053,
      "end_time": 128.6703645007924,
      "duration_seconds": 6.380348652931854,
      "height": 0.3702127659574468,
      "intensity_ratio": 0.6127659574468085,
      "average_value": 144.0
    },
    {
      "metric": "power",
      "zone": "Z1",
      "label": "Active Recovery",
      "start_time": 128.6703645007924,
      "end_time": 180.77654516640254,
      "duration_seconds": 40.408874801901746,
      "height": 0.27412806678204216,
      "intensity_ratio": 0.4238521836506159,
      "average_value": 99.60526315789474
    },
    {
      "metric": "power",
      "zone": "Z3",
      "label": "Tempo",
      "start_time": 180.77654516640254,
      "end_time": 186.09350237717908,
      "duration_seconds": 5.316957210776545,
      "height": 0.548113475177305,
      "intensity_ratio": 0.8229787234042554,
      "average_value": 193.4
    },
    {
      "metric": "power",
      "zone": "Z2",
      "label": "Endurance",
      "start_time": 186.09350237717908,
      "end_time": 198.8541996830428,
      "duration_seconds": 12.760697305863708,
      "height": 0.3826950354609928,
      "intensity_ratio": 0.628368794326241,
      "average_value": 147.66666666666666
    },
    {
      "metric": "power",
      "zone": "Z1",
      "label": "Active Recovery",
      "start_time": 198.8541996830428,
      "end_time": 233.946117274168,
      "duration_seconds": 23.394611727416798,
      "height": 0.29506593986284513,
      "intensity_ratio": 0.481431334622824,
      "average_value": 113.13636363636364
    },
    {
      "metric": "power",
      "zone": "Z1",
      "label": "Active Recovery",
      "start_time": 233.946117274168,
      "end_time": 257.3407290015848,
      "duration_seconds": 17.014263074484944,
      "height": 0.318936170212766,
      "intensity_ratio": 0.5470744680851064,
      "average_value": 128.5625
    },
    {
      "metric": "power",
      "zone": "Z1",
      "label": "Active Recovery",
      "start_time": 257.3407290015848,
      "end_time": 320.080824088748,
      "duration_seconds": 53.16957210776545,
      "height": 0.2649284332688588,
      "intensity_ratio": 0.3985531914893617,
      "average_value": 93.66
    },
    {
      "metric": "power",
      "zone": "Z1",
      "label": "Active Recovery",
      "start_time": 320.080824088748,
      "end_time": 338.15847860538827,
      "duration_seconds": 11.697305863708399,
      "height": 0.31117285036047126,
      "intensity_ratio": 0.525725338491296,
      "average_value": 123.54545454545455
    },
    {
      "metric": "power",
      "zone": "Z1",
      "label": "Active Recovery",
      "start_time": 338.15847860538827,
      "end_time": 424.29318541996827,
      "duration_seconds": 10.63391442155309,
      "height": 0.32,
      "intensity_ratio": 0.5770212765957446,
      "average_value": 135.6
    },
    {
      "metric": "power",
      "zone": "Z1",
      "label": "Active Recovery",
      "start_time": 424.29318541996827,
      "end_time": 454.0681458003169,
      "duration_seconds": 29.774960380348652,
      "height": 0.25390439347886157,
      "intensity_ratio": 0.36823708206686934,
      "average_value": 86.53571428571429
    },
    {
      "metric": "power",
      "zone": "Z1",
      "label": "Active Recovery",
      "start_time": 454.0681458003169,
      "end_time": 515.7448494453249,
      "duration_seconds": 61.67670364500792,
      "height": 0.23266591075835388,
      "intensity_ratio": 0.3098312545854732,
      "average_value": 72.8103448275862
    },
    {
      "metric": "power",
      "zone": "Z1",
      "label": "Active Recovery",
      "start_time": 518.9350237717908,
      "end_time": 585.9286846275753,
      "duration_seconds": 66.99366085578447,
      "height": 0.2387068250898038,
      "intensity_ratio": 0.3264437689969605,
      "average_value": 76.71428571428571
    },
    {
      "metric": "power",
      "zone": "Z1",
      "label": "Active Recovery",
      "start_time": 585.9286846275753,
      "end_time": 627.4009508716323,
      "duration_seconds": 41.47226624405705,
      "height": 0.25172642959877,
      "intensity_ratio": 0.36224768139661756,
      "average_value": 85.12820512820512
    },
    {
      "metric": "power",
      "zone": "Z1",
      "label": "Active Recovery",
      "start_time": 627.4009508716323,
      "end_time": 655.0491283676704,
      "duration_seconds": 27.648177496038034,
      "height": 0.2311144174973962,
      "intensity_ratio": 0.3055646481178396,
      "average_value": 71.8076923076923
    },
    {
      "metric": "power",
      "zone": "Z1",
      "label": "Active Recovery",
      "start_time": 655.0491283676704,
      "end_time": 767.7686212361331,
      "duration_seconds": 112.71949286846275,
      "height": 0.2643450968942739,
      "intensity_ratio": 0.3969490164592533,
      "average_value": 93.28301886792453
    },
    {
      "metric": "power",
      "zone": "Z1",
      "label": "Active Recovery",
      "start_time": 767.7686212361331,
      "end_time": 781.5927099841521,
      "duration_seconds": 13.824088748019017,
      "height": 0.29080791548876656,
      "intensity_ratio": 0.46972176759410805,
      "average_value": 110.38461538461539
    },
    {
      "metric": "power",
      "zone": "Z1",
      "label": "Active Recovery",
      "start_time": 781.5927099841521,
      "end_time": 842.2060221870047,
      "duration_seconds": 60.61331220285261,
      "height": 0.29602226068071535,
      "intensity_ratio": 0.4840612168719671,
      "average_value": 113.75438596491227
    },
    {
      "metric": "power",
      "zone": "Z1",
      "label": "Active Recovery",
      "start_time": 842.2060221870047,
      "end_time": 880.4881141045959,
      "duration_seconds": 38.282091917591124,
      "height": 0.270956372232968,
      "intensity_ratio": 0.4151300236406619,
      "average_value": 97.55555555555556
    },
    {
      "metric": "power",
      "zone": "Z1",
      "label": "Active Recovery",
      "start_time": 880.4881141045959,
      "end_time": 887.931854199683,
      "duration_seconds": 7.443740095087163,
      "height": 0.3036971539099198,
      "intensity_ratio": 0.5051671732522796,
      "average_value": 118.71428571428571
    },
    {
      "metric": "power",
      "zone": "Z2",
      "label": "Endurance",
      "start_time": 887.931854199683,
      "end_time": 911.3264659270998,
      "duration_seconds": 23.394611727416798,
      "height": 0.33833655705996124,
      "intensity_ratio": 0.5729206963249516,
      "average_value": 134.63636363636363
    },
    {
      "metric": "power",
      "zone": "Z1",
      "label": "Active Recovery",
      "start_time": 911.3264659270998,
      "end_time": 928.3407290015848,
      "duration_seconds": 17.014263074484944,
      "height": 0.31284332688588,
      "intensity_ratio": 0.5303191489361702,
      "average_value": 124.625
    },
    {
      "metric": "power",
      "zone": "Z2",
      "label": "Endurance",
      "start_time": 928.3407290015848,
      "end_time": 934.7210776545166,
      "duration_seconds": 6.380348652931854,
      "height": 0.3628368794326241,
      "intensity_ratio": 0.6035460992907802,
      "average_value": 141.83333333333334
    },
    {
      "metric": "power",
      "zone": "Z1",
      "label": "Active Recovery",
      "start_time": 934.7210776545166,
      "end_time": 944.2916006339144,
      "duration_seconds": 9.570522979397781,
      "height": 0.31806576402321085,
      "intensity_ratio": 0.5446808510638298,
      "average_value": 128.0
    },
    {
      "metric": "power",
      "zone": "Z1",
      "label": "Active Recovery",
      "start_time": 944.2916006339144,
      "end_time": 949.608557844691,
      "duration_seconds": 5.316957210776545,
      "height": 0.270715667311412,
      "intensity_ratio": 0.414468085106383,
      "average_value": 97.4
    },
    {
      "metric": "power",
      "zone": "Z2",
      "label": "Endurance",
      "start_time": 949.608557844691,
      "end_time": 962.3692551505546,
      "duration_seconds": 12.760697305863708,
      "height": 0.36482269503546094,
      "intensity_ratio": 0.6060283687943262,
      "average_value": 142.41666666666666
    },
    {
      "metric": "power",
      "zone": "Z1",
      "label": "Active Recovery",
      "start_time": 962.3692551505546,
      "end_time": 1000.6513470681458,
      "duration_seconds": 22.331220285261487,
      "height": 0.32,
      "intensity_ratio": 0.6149949341438703,
      "average_value": 144.52380952380952
    },
    {
      "metric": "power",
      "zone": "Z1",
      "label": "Active Recovery",
      "start_time": 1000.6513470681458,
      "end_time": 1027.2361331220286,
      "duration_seconds": 26.584786053882723,
      "height": 0.283651837524178,
      "intensity_ratio": 0.4500425531914894,
      "average_value": 105.76
    },
    {
      "metric": "power",
      "zone": "Z1",
      "label": "Active Recovery",
      "start_time": 1027.2361331220286,
      "end_time": 1227.1537242472266,
      "duration_seconds": 168.01584786053883,
      "height": 0.26755037582939545,
      "intensity_ratio": 0.40576353353083755,
      "average_value": 95.35443037974683
    },
    {
      "metric": "power",
      "zone": "Z2",
      "label": "Endurance",
      "start_time": 1227.1537242472266,
      "end_time": 1232.4706814580031,
      "duration_seconds": 5.316957210776545,
      "height": 0.4042553191489361,
      "intensity_ratio": 0.6553191489361702,
      "average_value": 154.0
    },
    {
      "metric": "power",
      "zone": "Z1",
      "label": "Active Recovery",
      "start_time": 1232.4706814580031,
      "end_time": 1257.9920760697305,
      "duration_seconds": 25.521394611727416,
      "height": 0.2837008381689233,
      "intensity_ratio": 0.450177304964539,
      "average_value": 105.79166666666667
    },
    {
      "metric": "power",
      "zone": "Z1",
      "label": "Active Recovery",
      "start_time": 1257.9920760697305,
      "end_time": 1285.6402535657685,
      "duration_seconds": 27.648177496038034,
      "height": 0.27259633983038234,
      "intensity_ratio": 0.41963993453355153,
      "average_value": 98.61538461538461
    },
    {
      "metric": "power",
      "zone": "Z1",
      "label": "Active Recovery",
      "start_time": 1285.6402535657685,
      "end_time": 1323.9223454833598,
      "duration_seconds": 38.282091917591124,
      "height": 0.289224156458199,
      "intensity_ratio": 0.4653664302600473,
      "average_value": 109.36111111111111
    },
    {
      "metric": "power",
      "zone": "Z1",
      "label": "Active Recovery",
      "start_time": 1323.9223454833598,
      "end_time": 1342.0,
      "duration_seconds": 18.07765451664025,
      "height": 0.29867789282057117,
      "intensity_ratio": 0.4913642052565707,
      "average_value": 115.47058823529412
    },
    {
      "metric": "power",
      "zone": "Z1",
      "label": "Active Recovery",
      "start_time": 1342.0,
      "end_time": 1439.8320126782885,
      "duration_seconds": 97.83201267828844,
      "height": 0.26819611470860316,
      "intensity_ratio": 0.4075393154486586,
      "average_value": 95.77173913043478
    },
    {
      "metric": "power",
      "zone": "Z1",
      "label": "Active Recovery",
      "start_time": 1439.8320126782885,
      "end_time": 1506.8256735340728,
      "duration_seconds": 66.99366085578447,
      "height": 0.2644229529335912,
      "intensity_ratio": 0.39716312056737585,
      "average_value": 93.33333333333333
    },
    {
      "metric": "power",
      "zone": "Z1",
      "label": "Active Recovery",
      "start_time": 1506.8256735340728,
      "end_time": 1531.283676703645,
      "duration_seconds": 24.45800316957211,
      "height": 0.2678092675132453,
      "intensity_ratio": 0.4064754856614246,
      "average_value": 95.52173913043478
    },
    {
      "metric": "power",
      "zone": "Z1",
      "label": "Active Recovery",
      "start_time": 1531.283676703645,
      "end_time": 1598.2773375594295,
      "duration_seconds": 66.99366085578447,
      "height": 0.2644229529335912,
      "intensity_ratio": 0.39716312056737585,
      "average_value": 93.33333333333333
    },
    {
      "metric": "power",
      "zone": "Z2",
      "label": "Endurance",
      "start_time": 1598.2773375594295,
      "end_time": 1629.1156893819334,
      "duration_seconds": 30.83835182250396,
      "height": 0.3447395451210565,
      "intensity_ratio": 0.5809244314013207,
      "average_value": 136.51724137931035
    },
    {
      "metric": "power",
      "zone": "Z2",
      "label": "Endurance",
      "start_time": 1629.1156893819334,
      "end_time": 1637.6228209191759,
      "duration_seconds": 8.507131537242472,
      "height": 0.3872340425531915,
      "intensity_ratio": 0.6340425531914894,
      "average_value": 149.0
    },
    {
      "metric": "power",
      "zone": "Z1",
      "label": "Active Recovery",
      "start_time": 1637.6228209191759,
      "end_time": 1652.5103011093502,
      "duration_seconds": 10.63391442155309,
      "height": 0.3104835589941973,
      "intensity_ratio": 0.5238297872340425,
      "average_value": 123.1
    },
    {
      "metric": "power",
      "zone": "Z2",
      "label": "Endurance",
      "start_time": 1652.5103011093502,
      "end_time": 1657.8272583201267,
      "duration_seconds": 5.316957210776545,
      "height": 0.38314893617021284,
      "intensity_ratio": 0.628936170212766,
      "average_value": 147.8
    },
    {
      "metric": "power",
      "zone": "Z1",
      "label": "Active Recovery",
      "start_time": 1657.8272583201267,
      "end_time": 1737.581616481775,
      "duration_seconds": 79.75435816164817,
      "height": 0.2534468085106383,
      "intensity_ratio": 0.3669787234042553,
      "average_value": 86.24
    },
    {
      "metric": "power",
      "zone": "Z1",
      "label": "Active Recovery",
      "start_time": 1742.8985736925515,
      "end_time": 1768.4199683042789,
      "duration_seconds": 25.521394611727416,
      "height": 0.2450161186331399,
      "intensity_ratio": 0.34379432624113476,
      "average_value": 80.79166666666667
    },
    {
      "metric": "power",
      "zone": "Z1",
      "label": "Active Recovery",
      "start_time": 1773.7369255150554,
      "end_time": 1868.378763866878,
      "duration_seconds": 94.6418383518225,
      "height": 0.2457383782843979,
      "intensity_ratio": 0.3457805402820942,
      "average_value": 81.25842696629213
    },
    {
      "metric": "power",
      "zone": "Z1",
      "label": "Active Recovery",
      "start_time": 1868.378763866878,
      "end_time": 1900.2805071315372,
      "duration_seconds": 31.90174326465927,
      "height": 0.30295293359123143,
      "intensity_ratio": 0.5031205673758865,
      "average_value": 118.23333333333333
    },
    {
      "metric": "power",
      "zone": "Z2",
      "label": "Endurance",
      "start_time": 1900.2805071315372,
      "end_time": 1909.851030110935,
      "duration_seconds": 9.570522979397781,
      "height": 0.4016075650118204,
      "intensity_ratio": 0.6520094562647755,
      "average_value": 153.22222222222223
    },
    {
      "metric": "power",
      "zone": "Z2",
      "label": "Endurance",
      "start_time": 1909.851030110935,
      "end_time": 1918.3581616481774,
      "duration_seconds": 8.507131537242472,
      "height": 0.41191489361702127,
      "intensity_ratio": 0.6648936170212766,
      "average_value": 156.25
    },
    {
      "metric": "power",
      "zone": "Z1",
      "label": "Active Recovery",
      "start_time": 1918.3581616481774,
      "end_time": 1934.309033280507,
      "duration_seconds": 15.950871632329635,
      "height": 0.3103288201160541,
      "intensity_ratio": 0.5234042553191489,
      "average_value": 123.0
    },
    {
      "metric": "power",
      "zone": "Z2",
      "label": "Endurance",
      "start_time": 1934.309033280507,
      "end_time": 1960.8938193343897,
      "duration_seconds": 26.584786053882723,
      "height": 0.3875063829787234,
      "intensity_ratio": 0.6343829787234043,
      "average_value": 149.08
    },
    {
      "metric": "power",
      "zone": "Z2",
      "label": "Endurance",
      "start_time": 1960.8938193343897,
      "end_time": 1987.4786053882726,
      "duration_seconds": 26.584786053882723,
      "height": 0.3698042553191489,
      "intensity_ratio": 0.6122553191489362,
      "average_value": 143.88
    },
    {
      "metric": "power",
      "zone": "Z2",
      "label": "Endurance",
      "start_time": 1987.4786053882726,
      "end_time": 2009.809825673534,
      "duration_seconds": 22.331220285261487,
      "height": 0.32903748733535965,
      "intensity_ratio": 0.5612968591691996,
      "average_value": 131.9047619047619
    },
    {
      "metric": "power",
      "zone": "Z2",
      "label": "Endurance",
      "start_time": 2009.809825673534,
      "end_time": 2021.5071315372425,
      "duration_seconds": 11.697305863708399,
      "height": 0.37206963249516434,
      "intensity_ratio": 0.6150870406189555,
      "average_value": 144.54545454545453
    },
    {
      "metric": "power",
      "zone": "Z3",
      "label": "Tempo",
      "start_time": 2021.5071315372425,
      "end_time": 2026.824088748019,
      "duration_seconds": 5.316957210776545,
      "height": 0.5473191489361701,
      "intensity_ratio": 0.822127659574468,
      "average_value": 193.2
    },
    {
      "metric": "power",
      "zone": "Z1",
      "label": "Active Recovery",
      "start_time": 2026.824088748019,
      "end_time": 2036.3946117274168,
      "duration_seconds": 9.570522979397781,
      "height": 0.3067182462927144,
      "intensity_ratio": 0.5134751773049646,
      "average_value": 120.66666666666667
    },
    {
      "metric": "power",
      "zone": "Z1",
      "label": "Active Recovery",
      "start_time": 2036.3946117274168,
      "end_time": 2047.0285261489698,
      "duration_seconds": 10.63391442155309,
      "height": 0.275357833655706,
      "intensity_ratio": 0.42723404255319153,
      "average_value": 100.4
    },
    {
      "metric": "power",
      "zone": "Z1",
      "label": "Active Recovery",
      "start_time": 2052.3454833597466,
      "end_time": 2062.9793977812997,
      "duration_seconds": 10.63391442155309,
      "height": 0.24193423597678915,
      "intensity_ratio": 0.3353191489361702,
      "average_value": 78.8
    },
    {
      "metric": "power",
      "zone": "Z1",
      "label": "Active Recovery",
      "start_time": 2068.296354992076,
      "end_time": 2076.8034865293184,
      "duration_seconds": 8.507131537242472,
      "height": 0.26119922630560927,
      "intensity_ratio": 0.3882978723404255,
      "average_value": 91.25
    },
    {
      "metric": "power",
      "zone": "Z1",
      "label": "Active Recovery",
      "start_time": 2076.8034865293184,
      "end_time": 2127.846275752773,
      "duration_seconds": 20.204437400950873,
      "height": 0.2845933014354067,
      "intensity_ratio": 0.4526315789473684,
      "average_value": 106.36842105263158
    },
    {
      "metric": "power",
      "zone": "Z1",
      "label": "Active Recovery",
      "start_time": 2127.846275752773,
      "end_time": 2135.2900158478606,
      "duration_seconds": 7.443740095087163,
      "height": 0.26213871235147834,
      "intensity_ratio": 0.39088145896656534,
      "average_value": 91.85714285714286
    },
    {
      "metric": "power",
      "zone": "Z1",
      "label": "Active Recovery",
      "start_time": 2209.727416798732,
      "end_time": 2237.37559429477,
      "duration_seconds": 27.648177496038034,
      "height": 0.2762862669245648,
      "intensity_ratio": 0.4297872340425532,
      "average_value": 101.0
    },
    {
      "metric": "power",
      "zone": "Z2",
      "label": "Endurance",
      "start_time": 2237.37559429477,
      "end_time": 2253.3264659271,
      "duration_seconds": 15.950871632329635,
      "height": 0.36953191489361703,
      "intensity_ratio": 0.6119148936170213,
      "average_value": 143.8
    },
    {
      "metric": "power",
      "zone": "Z1",
      "label": "Active Recovery",
      "start_time": 2253.3264659271,
      "end_time": 2310.7496038034865,
      "duration_seconds": 31.90174326465927,
      "height": 0.32,
      "intensity_ratio": 0.6109219858156029,
      "average_value": 143.56666666666666
    },
    {
      "metric": "power",
      "zone": "Z1",
      "label": "Active Recovery",
      "start_time": 2310.7496038034865,
      "end_time": 2343.7147385103012,
      "duration_seconds": 25.521394611727416,
      "height": 0.32,
      "intensity_ratio": 0.5551418439716312,
      "average_value": 130.45833333333334
    },
    {
      "metric": "power",
      "zone": "Z3",
      "label": "Tempo",
      "start_time": 2343.7147385103012,
      "end_time": 2351.158478605388,
      "duration_seconds": 7.443740095087163,
      "height": 0.48,
      "intensity_ratio": 0.7003039513677812,
      "average_value": 164.57142857142858
    },
    {
      "metric": "power",
      "zone": "Z2",
      "label": "Endurance",
      "start_time": 2351.158478605388,
      "end_time": 2363.919175911252,
      "duration_seconds": 12.760697305863708,
      "height": 0.34127659574468083,
      "intensity_ratio": 0.5765957446808511,
      "average_value": 135.5
    },
    {
      "metric": "power",
      "zone": "Z1",
      "label": "Active Recovery",
      "start_time": 2363.919175911252,
      "end_time": 2383.0602218700474,
      "duration_seconds": 11.697305863708399,
      "height": 0.3072340425531915,
      "intensity_ratio": 0.5148936170212766,
      "average_value": 121.0
    },
    {
      "metric": "power",
      "zone": "Z1",
      "label": "Active Recovery",
      "start_time": 2383.0602218700474,
      "end_time": 2456.434231378764,
      "duration_seconds": 28.711568938193345,
      "height": 0.2766301310982162,
      "intensity_ratio": 0.4307328605200946,
      "average_value": 101.22222222222223
    },
    {
      "metric": "power",
      "zone": "Z1",
      "label": "Active Recovery",
      "start_time": 2456.434231378764,
      "end_time": 2470.258320126783,
      "duration_seconds": 9.570522979397781,
      "height": 0.2635632924994627,
      "intensity_ratio": 0.3947990543735224,
      "average_value": 92.77777777777777
    },
    {
      "metric": "power",
      "zone": "Z1",
      "label": "Active Recovery",
      "start_time": 2470.258320126783,
      "end_time": 2503.2234548335973,
      "duration_seconds": 23.394611727416798,
      "height": 0.25638122032706173,
      "intensity_ratio": 0.37504835589941976,
      "average_value": 88.13636363636364
    },
    {
      "metric": "power",
      "zone": "Z1",
      "label": "Active Recovery",
      "start_time": 2503.2234548335973,
      "end_time": 2511.73058637084,
      "duration_seconds": 8.507131537242472,
      "height": 0.2635203094777563,
      "intensity_ratio": 0.3946808510638298,
      "average_value": 92.75
    },
    {
      "metric": "power",
      "zone": "Z1",
      "label": "Active Recovery",
      "start_time": 2517.0475435816165,
      "end_time": 2524.4912836767035,
      "duration_seconds": 7.443740095087163,
      "height": 0.25594915722575295,
      "intensity_ratio": 0.3738601823708207,
      "average_value": 87.85714285714286
    },
    {
      "metric": "power",
      "zone": "Z1",
      "label": "Active Recovery",
      "start_time": 2527.6814580031696,
      "end_time": 2537.251980982567,
      "duration_seconds": 9.570522979397781,
      "height": 0.26132817537072855,
      "intensity_ratio": 0.38865248226950355,
      "average_value": 91.33333333333333
    },
    {
      "metric": "power",
      "zone": "Z1",
      "label": "Active Recovery",
      "start_time": 2537.251980982567,
      "end_time": 2562.7733755942945,
      "duration_seconds": 18.07765451664025,
      "height": 0.2539856638980544,
      "intensity_ratio": 0.3684605757196496,
      "average_value": 86.58823529411765
    },
    {
      "metric": "power",
      "zone": "Z1",
      "label": "Active Recovery",
      "start_time": 2562.7733755942945,
      "end_time": 2586.1679873217117,
      "duration_seconds": 14.887480190174326,
      "height": 0.2530754352030947,
      "intensity_ratio": 0.3659574468085106,
      "average_value": 86.0
    },
    {
      "metric": "power",
      "zone": "Z1",
      "label": "Active Recovery",
      "start_time": 2591.484944532488,
      "end_time": 2604.2456418383517,
      "duration_seconds": 6.380348652931854,
      "height": 0.22651192778852353,
      "intensity_ratio": 0.2929078014184397,
      "average_value": 68.83333333333333
    },
    {
      "metric": "power",
      "zone": "Z1",
      "label": "Active Recovery",
      "start_time": 2604.2456418383517,
      "end_time": 2628.703645007924,
      "duration_seconds": 20.204437400950873,
      "height": 0.2642329227323629,
      "intensity_ratio": 0.3966405375139978,
      "average_value": 93.21052631578948
    }
  ]
}